{
    "zh-CN": {
        "images": [
            {
                "startdate": "20210301", 
                "urlbase": "/th?id=OHR.VolcanoLlaima_ZH-CN3436127573", 
                "fullstartdate": "202103011600", 
                "copyright": "亚伊马火山与前景中的智利南洋杉，智利孔吉利奥国家公园 (© Fotografías Jorge León Cabello/Getty Images)", 
                "title": "", 
                "url": "/th?id=OHR.VolcanoLlaima_ZH-CN3436127573_1920x1080.jpg&rf=LaDigue_1920x1080.jpg&pid=hp", 
                "hs": [], 
                "hsh": "95e9d738c3cef21188fb4fadba095037", 
                "bot": 1, 
                "quiz": "/search?q=Bing+homepage+quiz&filters=WQOskey:%22HPQuiz_20210301_VolcanoLlaima%22&FORM=HPQUIZ", 
                "drk": 1, 
                "copyrightlink": "https://www.bing.com/search?q=%E4%BA%9A%E4%BC%8A%E9%A9%AC%E7%81%AB%E5%B1%B1&form=hpcapt&mkt=zh-cn", 
                "wp": true, 
                "enddate": "20210302", 
                "top": 1
            }
        ], 
        "tooltips": {
            "play": "播放视频", 
            "loading": "正在加载...", 
            "walle": "此图片不能下载用作壁纸。", 
            "next": "下一个图像", 
            "walls": "下载今日美图。仅限用作桌面壁纸。", 
            "pause": "暂停视频", 
            "previous": "上一个图像"
        }
    }, 
    "en-US": {
        "images": [
            {
                "startdate": "20210301", 
                "urlbase": "/th?id=OHR.IdaBWells_EN-US0043525265", 
                "fullstartdate": "202103010800", 
                "copyright": "A section of a large mosaic of Ida B. Wells displayed at Union Station in Washington, DC, in August 2020 (© Manuel Balce Ceneta/AP Photo)", 
                "title": "Gazing upon 'Portraits of Change'", 
                "url": "/th?id=OHR.IdaBWells_EN-US0043525265_1920x1080.jpg&rf=LaDigue_1920x1080.jpg&pid=hp", 
                "hs": [], 
                "hsh": "295dd661456d888c693f4f6969331942", 
                "bot": 1, 
                "quiz": "/search?q=Bing+homepage+quiz&filters=WQOskey:%22HPQuiz_20210301_IdaBWells%22&FORM=HPQUIZ", 
                "drk": 1, 
                "copyrightlink": "https://www.bing.com/search?q=women%27s+history+month&form=hpcapt&filters=HpDate%3a%2220210301_0800%22", 
                "wp": false, 
                "enddate": "20210302", 
                "top": 1
            }
        ], 
        "tooltips": {
            "play": "Play video", 
            "loading": "Loading...", 
            "walle": "This image is not available to download as wallpaper.", 
            "next": "Next image", 
            "walls": "Download this image. Use of this image is restricted to wallpaper only.", 
            "pause": "Pause video", 
            "previous": "Previous image"
        }
    }
}