{
    "zh-CN": {
        "images": [
            {
                "startdate": "20210402", 
                "urlbase": "/th?id=OHR.AnivaLighthouse_ZH-CN3021410274", 
                "fullstartdate": "202104021600", 
                "copyright": "阿尼瓦角的灯塔，俄罗斯萨哈林岛 (© Amazing Aerial Agency/Offset by Shutterstock)", 
                "title": "", 
                "url": "/th?id=OHR.AnivaLighthouse_ZH-CN3021410274_1920x1080.jpg&rf=LaDigue_1920x1080.jpg&pid=hp", 
                "hs": [], 
                "hsh": "ae203b614244eb46522ac781b532881c", 
                "bot": 1, 
                "quiz": "/search?q=Bing+homepage+quiz&filters=WQOskey:%22HPQuiz_20210402_AnivaLighthouse%22&FORM=HPQUIZ", 
                "drk": 1, 
                "copyrightlink": "https://www.bing.com/search?q=%E9%98%BF%E5%B0%BC%E7%93%A6%E7%81%AF%E5%A1%94&form=hpcapt&mkt=zh-cn", 
                "wp": true, 
                "enddate": "20210403", 
                "top": 1
            }
        ], 
        "tooltips": {
            "play": "播放视频", 
            "loading": "正在加载...", 
            "walle": "此图片不能下载用作壁纸。", 
            "next": "下一个图像", 
            "walls": "下载今日美图。仅限用作桌面壁纸。", 
            "pause": "暂停视频", 
            "previous": "上一个图像"
        }
    }, 
    "en-US": {
        "images": [
            {
                "startdate": "20210402", 
                "urlbase": "/th?id=OHR.BrazilSandDunes_EN-US8030598740", 
                "fullstartdate": "202104020700", 
                "copyright": "Lençóis Maranhenses National Park in the state of Maranhão, Brazil (© WIN-Initiative/Getty Images)", 
                "title": "White dunes, blue lagoons", 
                "url": "/th?id=OHR.BrazilSandDunes_EN-US8030598740_1920x1080.jpg&rf=LaDigue_1920x1080.jpg&pid=hp", 
                "hs": [], 
                "hsh": "bc26030cc20533f70a4840f22caab4fc", 
                "bot": 1, 
                "quiz": "/search?q=Bing+homepage+quiz&filters=WQOskey:%22HPQuiz_20210402_BrazilSandDunes%22&FORM=HPQUIZ", 
                "drk": 1, 
                "copyrightlink": "https://www.bing.com/search?q=lencois+maranhenses+national+park&form=hpcapt&filters=HpDate%3a%2220210402_0700%22", 
                "wp": true, 
                "enddate": "20210403", 
                "top": 1
            }
        ], 
        "tooltips": {
            "play": "Play video", 
            "loading": "Loading...", 
            "walle": "This image is not available to download as wallpaper.", 
            "next": "Next image", 
            "walls": "Download this image. Use of this image is restricted to wallpaper only.", 
            "pause": "Pause video", 
            "previous": "Previous image"
        }
    }
}